oakscript/__init__.py
oakscript/screener.py
oakscript/pinescript/__init__.py
oakscript/pinescript/ta.py
oakscript/strategytester/__init__.py
oakscript/strategytester/reports/__init__.py
tests/__init__.py
tests/integration/__init__.py
tests/strategies/__init__.py
tests/strategies/rsi.py
oakscript-0.1.0.dist-info/METADATA
oakscript-0.1.0.dist-info/WHEEL
oakscript-0.1.0.dist-info/top_level.txt
oakscript-0.1.0.dist-info/RECORD
