Metadata-Version: 2.1
Name: oakscript
Version: 0.1.0
Summary: Simulate TradingView Strategy Tester with Python strategy script
Author: houseofai
Keywords: python,pinescript,tradingview
Classifier: Development Status :: 3 - Alpha
Classifier: Intended Audience :: Education
Classifier: Programming Language :: Python :: 2
Classifier: Programming Language :: Python :: 3
Classifier: Operating System :: MacOS :: MacOS X
Classifier: Operating System :: Microsoft :: Windows
